matrix_calculus/__init__.py
matrix_calculus/matrix_calculus.py
matrix_calculus-0.0.7.dist-info/METADATA
matrix_calculus-0.0.7.dist-info/WHEEL
matrix_calculus-0.0.7.dist-info/top_level.txt
matrix_calculus-0.0.7.dist-info/RECORD
