Metadata-Version: 2.1
Name: matrix-calculus
Version: 0.0.7
Summary: Use python to take derivative of matrix equations!
Home-page: https://github.com/songlinhou/matrix_calculus
Author: Ray Hou (Songlin Hou)
Author-email: songlinhou1993@gmail.com
License: UNKNOWN
Keywords: matrix,calculus
Platform: UNKNOWN
Requires-Dist: requests
